MANIFEST.in
README.md
setup.py
daum_openapi/__init__.py
daum_openapi.egg-info/PKG-INFO
daum_openapi.egg-info/SOURCES.txt
daum_openapi.egg-info/dependency_links.txt
daum_openapi.egg-info/entry_points.txt
daum_openapi.egg-info/not-zip-safe
daum_openapi.egg-info/requires.txt
daum_openapi.egg-info/top_level.txt
daum_openapi/common/__init__.py
daum_openapi/common/request.py
daum_openapi/contents/__init__.py
daum_openapi/contents/contents.py
daum_openapi/json_object/__init__.py
daum_openapi/json_object/json_object.py
daum_openapi/local/__init__.py
daum_openapi/local/local.py
daum_openapi/search/__init__.py
daum_openapi/search/search.py
daum_openapi/shopping/__init__.py
daum_openapi/shopping/shopping.py
daum_openapi/socialpick/__init__.py
daum_openapi/socialpick/socialpick.py