Metadata-Version: 1.1
Name: daum-openapi
Version: 0.1
Summary: Python Library of Daum Open Data API
Home-page: https://github.com/AhnSeongHyun/daum_openapi
Author: SeongHyun.Ahn
Author-email: sh84.ahn@gmail.com
License: MIT
Keywords: daum openapi
Platform: UNKNOWN
Classifier: Development Status :: 3 - Alpha
Classifier: Intended Audience :: Developers
Classifier: Programming Language :: Python
Classifier: Topic :: Text Processing :: Markup :: HTML
Classifier: Topic :: Software Development :: Libraries :: Python Modules
